sc_oa-0.7.0.17.dist-info/licenses/LICENSE
sphinxcontrib/__init__.py
sphinxcontrib/openapi/__init__.py
sphinxcontrib/openapi/__main__.py
sphinxcontrib/openapi/_lib2to3.py
sphinxcontrib/openapi/directive.py
sphinxcontrib/openapi/openapi20.py
sphinxcontrib/openapi/openapi30.py
sphinxcontrib/openapi/schema_utils.py
sphinxcontrib/openapi/utils.py
sphinxcontrib/openapi/locale/openapi.pot
sphinxcontrib/openapi/locale/es_ES/LC_MESSAGES/openapi.mo
sphinxcontrib/openapi/locale/es_ES/LC_MESSAGES/openapi.po
sphinxcontrib/openapi/locale/fr_FR/LC_MESSAGES/openapi.mo
sphinxcontrib/openapi/locale/fr_FR/LC_MESSAGES/openapi.po
sphinxcontrib/openapi/renderers/__init__.py
sphinxcontrib/openapi/renderers/_description.py
sphinxcontrib/openapi/renderers/_httpdomain.py
sphinxcontrib/openapi/renderers/_httpdomain_old.py
sphinxcontrib/openapi/renderers/_model.py
sphinxcontrib/openapi/renderers/_toc.py
sphinxcontrib/openapi/renderers/abc.py
sc_oa-0.7.0.17.dist-info/METADATA
sc_oa-0.7.0.17.dist-info/WHEEL
sc_oa-0.7.0.17.dist-info/top_level.txt
sc_oa-0.7.0.17.dist-info/RECORD
