Metadata-Version: 2.4
Name: sc-oa
Version: 0.7.0.17
Summary: Fork of the OpenAPI (fka Swagger) spec renderer for Sphinx
Home-page: https://github.com/olivier-heurtier/sphinxcontrib-openapi/tree/mymaster
Author: Olivier Heurtier
Author-email: olivier.heurtier@github.com
License: BSD
Classifier: Topic :: Documentation
Classifier: Topic :: Documentation :: Sphinx
Classifier: License :: OSI Approved :: BSD License
Classifier: Environment :: Console
Classifier: Intended Audience :: Developers
Classifier: Operating System :: OS Independent
Classifier: Programming Language :: Python
Classifier: Programming Language :: Python :: 3
Classifier: Programming Language :: Python :: 3 :: Only
Classifier: Programming Language :: Python :: 3.10
Classifier: Programming Language :: Python :: 3.11
Classifier: Programming Language :: Python :: 3.12
Classifier: Programming Language :: Python :: 3.13
Classifier: Programming Language :: Python :: Implementation :: CPython
Classifier: Framework :: Sphinx
Classifier: Framework :: Sphinx :: Extension
Requires-Python: >=3.10
License-File: LICENSE
Requires-Dist: sphinx
Requires-Dist: sphinxcontrib-httpdomain
Requires-Dist: PyYAML
Requires-Dist: jsonschema
Requires-Dist: m2r2
Requires-Dist: picobox
Requires-Dist: deepmerge
Requires-Dist: setuptools
Dynamic: license-file
